winbox/__init__.py
winbox/main.py
winbox-0.2.0.dist-info/LICENSE
winbox-0.2.0.dist-info/WHEEL
winbox-0.2.0.dist-info/METADATA
winbox-0.2.0.dist-info/RECORD
