Metadata-Version: 2.1
Name: winbox
Version: 0.2.0
Summary: A lightweight helper for creating windows message boxes.
Author-email: hazyfossa <hazyfossa@gmail.com>
Requires-Python: >=3.8
Classifier: Programming Language :: Python :: 3
Classifier: License :: OSI Approved :: MIT License
Classifier: Operating System :: Microsoft :: Windows
Classifier: Intended Audience :: Developers
Classifier: Development Status :: 4 - Beta
Project-URL: Homepage, https://github.com/hazyfossa/winbox
Project-URL: Issues, https://github.com/hazyfossa/winbox/issues
